locbuf
