Metadata-Version: 1.0
Name: locbuf
Version: 0.0.11
Summary: local buffer decorator for api request (pd.DataFrame)
Home-page: https://github.com/wenzhuart/locbuf
Author: bamboo
Author-email: wenzhu_art@hotmail.com
License: UNKNOWN
Platform: UNKNOWN
